crawler/__init__.py
crawler/application/__init__.py
crawler/application/interfaces/__init__.py
crawler/application/interfaces/formatter.py
crawler/application/interfaces/observer.py
crawler/application/interfaces/platform_client.py
crawler/application/interfaces/repository.py
crawler/application/use_cases/__init__.py
crawler/application/use_cases/batch_download.py
crawler/application/use_cases/fetch_problem.py
crawler/application/use_cases/list_problems.py
crawler/cli/main.py
crawler/cli/commands/__init__.py
crawler/cli/commands/base.py
crawler/cli/commands/batch.py
crawler/cli/commands/download.py
crawler/cli/commands/list.py
crawler/cli/observers/__init__.py
crawler/cli/observers/console_progress.py
crawler/cli/observers/logging_observer.py
crawler/config/__init__.py
crawler/config/logging_config.py
crawler/config/settings.py
crawler/domain/__init__.py
crawler/domain/exceptions.py
crawler/domain/entities/__init__.py
crawler/domain/entities/enums.py
crawler/domain/entities/problem.py
crawler/domain/entities/submission.py
crawler/domain/entities/user.py
crawler/domain/value_objects/__init__.py
crawler/domain/value_objects/constraint.py
crawler/domain/value_objects/difficulty.py
crawler/domain/value_objects/example.py
crawler/domain/value_objects/percentiles.py
crawler/infrastructure/formatters/__init__.py
crawler/infrastructure/formatters/json_formatter.py
crawler/infrastructure/formatters/markdown_formatter.py
crawler/infrastructure/formatters/python_formatter.py
crawler/infrastructure/formatters/text_utils.py
crawler/infrastructure/http/__init__.py
crawler/infrastructure/http/client.py
crawler/infrastructure/http/rate_limiter.py
crawler/infrastructure/http/retry_config.py
crawler/infrastructure/platforms/__init__.py
crawler/infrastructure/platforms/factory.py
crawler/infrastructure/platforms/leetcode/__init__.py
crawler/infrastructure/platforms/leetcode/adapter.py
crawler/infrastructure/platforms/leetcode/client.py
crawler/infrastructure/repositories/__init__.py
coding_platform_crawler-2.0.3.dist-info/METADATA
coding_platform_crawler-2.0.3.dist-info/WHEEL
coding_platform_crawler-2.0.3.dist-info/entry_points.txt
coding_platform_crawler-2.0.3.dist-info/top_level.txt
coding_platform_crawler-2.0.3.dist-info/RECORD
