Metadata-Version: 2.4
Name: coding-platform-crawler
Version: 2.0.3
Summary: A well-architected, extensible Python toolkit for downloading and managing coding problems from LeetCode and other platforms
Author-email: Prakhar Mishra <prakharmishra04@users.noreply.github.com>
License: MIT
Project-URL: Homepage, https://github.com/prakharmishra04/extensible-leetcode-crawler
Project-URL: Documentation, https://github.com/prakharmishra04/extensible-leetcode-crawler#readme
Project-URL: Repository, https://github.com/prakharmishra04/extensible-leetcode-crawler
Project-URL: Issues, https://github.com/prakharmishra04/extensible-leetcode-crawler/issues
Keywords: leetcode,crawler,coding,problems,solutions,scraper
Classifier: Development Status :: 4 - Beta
Classifier: Intended Audience :: Developers
Classifier: License :: OSI Approved :: MIT License
Classifier: Programming Language :: Python :: 3
Classifier: Programming Language :: Python :: 3.8
Classifier: Programming Language :: Python :: 3.9
Classifier: Programming Language :: Python :: 3.10
Classifier: Programming Language :: Python :: 3.11
Classifier: Programming Language :: Python :: 3.12
Classifier: Topic :: Software Development :: Libraries :: Python Modules
Classifier: Topic :: Utilities
Requires-Python: >=3.8
Requires-Dist: requests>=2.31.0
Requires-Dist: beautifulsoup4>=4.12.0
Requires-Dist: lxml>=4.9.0
Requires-Dist: pyyaml>=6.0
Requires-Dist: rich>=13.0.0
Provides-Extra: dev
Requires-Dist: pytest>=7.4.0; extra == "dev"
Requires-Dist: pytest-cov>=4.1.0; extra == "dev"
Requires-Dist: pytest-mock>=3.11.0; extra == "dev"
Requires-Dist: hypothesis>=6.82.0; extra == "dev"
Requires-Dist: black>=23.7.0; extra == "dev"
Requires-Dist: flake8>=6.1.0; extra == "dev"
Requires-Dist: flake8-bugbear>=23.7.0; extra == "dev"
Requires-Dist: flake8-comprehensions>=3.14.0; extra == "dev"
Requires-Dist: flake8-simplify>=0.20.0; extra == "dev"
Requires-Dist: mypy>=1.4.0; extra == "dev"
Requires-Dist: isort>=5.12.0; extra == "dev"
Requires-Dist: pre-commit>=3.3.0; extra == "dev"
Requires-Dist: bandit>=1.7.5; extra == "dev"
Requires-Dist: pydocstyle>=6.3.0; extra == "dev"
Requires-Dist: types-requests>=2.31.0; extra == "dev"
Requires-Dist: types-PyYAML>=6.0.0; extra == "dev"
